fgr/__init__.py
fgr/commands/__init__.py
fgr/core/__init__.py
fgr/core/_fields.py
fgr/core/codec.py
fgr/core/constants.py
fgr/core/enums.py
fgr/core/exceptions.py
fgr/core/fields.py
fgr/core/log.py
fgr/core/meta.py
fgr/core/modules.py
fgr/core/objects.py
fgr/core/patterns.py
fgr/core/query.py
fgr/core/utils.py
fgr/core/dtypes/__init__.py
fgr/core/dtypes/constants.py
fgr/core/dtypes/utils.py
fgr/docs/__init__.py
fgr/docs/commands/__init__.py
fgr/docs/static/__init__.py
fgr/docs/static/conf.tpl
fgr/docs/static/favicon.ico
fgr/docs/static/logo.png
tests/core/__init__.py
tests/core/_fields_test.py
tests/core/codec_test.py
tests/core/exceptions_test.py
tests/core/fields_test.py
tests/core/logger_test.py
tests/core/meta_test.py
tests/core/objects_test.py
tests/core/query_test.py
tests/core/readme_test.py
tests/core/utils_test.py
tests/core/dtypes/init_test.py
tests/core/mocking/__init__.py
tests/core/mocking/examples.py
fgr-0.4.5.dist-info/LICENSE
fgr-0.4.5.dist-info/METADATA
fgr-0.4.5.dist-info/WHEEL
fgr-0.4.5.dist-info/entry_points.txt
fgr-0.4.5.dist-info/top_level.txt
fgr-0.4.5.dist-info/RECORD
