Metadata-Version: 2.1
Name: fgr
Version: 0.4.5
Summary: Zero-dependency Python framework for object oriented development.
Author-email: Dan <dan@1howardcapital.com>
Maintainer-email: Dan <dan@1howardcapital.com>
Project-URL: Documentation, https://fgr.readthedocs.io/en/stable/fgr.html
Project-URL: Homepage, https://fgr.readthedocs.io/en/stable/
Project-URL: Repository, https://github.com/dan1hc/fgr.git
Project-URL: Issues, https://github.com/dan1hc/fgr/issues
Project-URL: Changelog, https://github.com/dan1hc/fgr/blob/main/CHANGELOG.md
Keywords: fgr,framework,rest
Classifier: Development Status :: 5 - Production/Stable
Classifier: License :: OSI Approved :: GNU Library or Lesser General Public License (LGPL)
Classifier: Operating System :: OS Independent
Classifier: Programming Language :: Python :: 3.11
Classifier: Programming Language :: Python :: 3.12
Classifier: Topic :: Software Development :: Libraries :: Application Frameworks
Classifier: Typing :: Typed
Requires-Python: >=3.10
License-File: LICENSE
Provides-Extra: develop
Requires-Dist: mypy ; extra == 'develop'
Requires-Dist: pre-commit ; extra == 'develop'
Requires-Dist: coverage ; extra == 'develop'
Requires-Dist: pytest ; extra == 'develop'
Requires-Dist: pytest-cov ; extra == 'develop'
Requires-Dist: ruff ; extra == 'develop'
Provides-Extra: docs
Requires-Dist: commonmark ==0.9.* ; extra == 'docs'
Requires-Dist: sphinx ==7.* ; extra == 'docs'
